storagy/__init__.py
storagy/filter.py
storagy/utils.py
storagy/conn/__init__.py
storagy/conn/csv.py
storagy/conn/directory.py
storagy/conn/excel.py
storagy/conn/flatfile.py
storagy/conn/sqlserver.py
storagy-1.0.1.dev1.dist-info/LICENSE
storagy-1.0.1.dev1.dist-info/METADATA
storagy-1.0.1.dev1.dist-info/WHEEL
storagy-1.0.1.dev1.dist-info/top_level.txt
storagy-1.0.1.dev1.dist-info/RECORD
